<?xml version="1.0" encoding="utf-8"?>
<lazycms>
    <title>會員管理</title>
    <version memo="版本">1.0</version>
    <author memo="作者">Lukin</author>
    <email memo="作者常用郵箱，以便聯系">mylukin@gmail.com</email>
    <source memo="作者來自哪裏？">http://www.lazycms.net</source>
    <manage>url('Passport')</manage>
    

    <common>
        <addgroup>添加用戶組</addgroup>
        <adduser>添加用戶</adduser>
        <editgroup>編輯用戶組</editgroup>
        <leadin>導入組模型</leadin>
    </common>

    <list>
        <group title="用戶組列表">
            <id>ID</id>
            <name>用戶組</name>
            <ename>組標識</ename>
            <addtable>附加表</addtable>
            <state>狀態</state>
            <count>用戶數</count>
            <action>操作</action>
        </group>
    </list>

    <label>
        <leadin>請選擇組模型文件 (xml格式文件)</leadin>
        <group>
            <name>用戶組名稱</name>
            <ename>用戶組標識 (字母、數字、下劃線；添加後不可修改)</ename>
            <fieldset>字段配置</fieldset>
            <fieldtip><![CDATA[添加用戶組後，點擊 <img src="{$root}/system/images/os/fields.gif" class="os"/> 圖標進行字段管理]]></fieldtip>
        </group>
    </label>

    <check>
        <group>
            <name>用戶組名稱不能為空</name>
            <ename>用戶組標識不能為空</ename>
            <ename1>只允許輸入：字母、數字、下劃線</ename1>
        </group>
    </check>

    <pop>
        <group>
            <select>請選擇一個用戶組</select>
            <deleteok>成功刪除您選擇的用戶組</deleteok>
            <deletefieldok>成功刪除您選擇的字段</deletefieldok>
            <deletefielderr>數據庫字段可能已經被刪除</deletefielderr>
        </group>
    </pop>
</lazycms>